log2tg/__init__.py
log2tg/formatters.py
log2tg/handlers.py
logging2telegram-1.0.4.dist-info/LICENSE
logging2telegram-1.0.4.dist-info/METADATA
logging2telegram-1.0.4.dist-info/WHEEL
logging2telegram-1.0.4.dist-info/top_level.txt
logging2telegram-1.0.4.dist-info/RECORD
