Metadata-Version: 2.1
Name: logging2telegram
Version: 1.0.4
Summary: Telegram logging handler
Home-page: https://github.com/tezmen/loging2telegram
Author: tezmen
License: Apache License, Version 2.0, see LICENSE file
Platform: UNKNOWN
Classifier: License :: OSI Approved :: Apache Software License
Classifier: Operating System :: OS Independent
Classifier: Environment :: Console
Classifier: Development Status :: 3 - Alpha
Classifier: Programming Language :: Python
Classifier: Programming Language :: Python :: 3.7
Classifier: Programming Language :: Python :: Implementation :: PyPy
Requires-Dist: requests (>=2.21.0)
